{"v":1,"updated":"2026-07-12T04:53:52.860Z","store":{"d9g4yo6":[],"dmclck9":[{"id":"gzbsidua","dateAdded":"2026-07-10","me":2,"onPlay":true,"mulligan":5,"myLore":20,"oppLore":6,"margin":14,"cross10":19,"cross20":23,"cross10MyTurn":10,"firstQuest":13,"firstQuestMyTurn":7,"myTurns":12,"gameTurns":23,"lorePerTurn":1.67,"result":"W","method":"20 lore","removedByMe":13,"myLost":8,"questers":{"Chip - Retrieval Expert":5,"Bambi - Ethereal Fawn":1,"Scrooge McDuck - Ghostly Ebenezer":5,"Grandmother Willow - Ancient Advisor":2,"Dale - Ready for His Shot":6,"Gaston - Frightful Bully":1},"combos":{},"loreByTurn":{"13":1,"15":3,"17":8,"19":13,"21":19,"23":20},"oppLoreByTurn":{"8":1,"12":2,"16":5,"22":6},"oppCards":["Darkwing Duck - Darkwolf Dog","Dash Parr - Super Speedy","Edna Mode - Fashion Designer","Elsa - The Fifth Spirit","Jack-Jack Parr - Incredible Potential","Liquidator - Iced Over","Mr. Incredible - Bob Parr","Mr. Incredible - Super Strong","Mrs. Incredible - Super Stretchy","Mulan - Elite Archer","Mulan - Injured Soldier","Queen of Hearts - Sensing Weakness","Super Suit","The Headless Horseman - Terror of Sleepy Hollow","Violet Parr - Learning New Powers"],"archetype":"Ruby/Amethyst","winCat":"Dale + Mulan board clear","lossCat":"","venue":"","notes":"","parserVersion":2,"rawHash":"ada73b94756300b1465f","planScore":{"score":70,"label":"Partly on plan","reasons":[]},"winCondition":{"primary":"Combo payoff","secondary":"Board control into lore","evidence":["Combo flag \"tripleShot\" fired and you closed the game."],"confidence":0.7},"lossCondition":{"primary":"","secondary":"","evidence":[],"confidence":0},"keyTurningPoints":[{"turn":13,"label":"First quest","evidence":"Your first quest landed on turn 13 (your turn 7).","impact":"positive"},{"turn":17,"label":"Big lore swing (you)","evidence":"+5 lore in one step (turn 17), reaching 8.","impact":"positive"},{"turn":19,"label":"Crossed 10 lore","evidence":"Reached 10 lore on turn 19 (your turn 10).","impact":"positive"},{"turn":19,"label":"Big lore swing (you)","evidence":"+5 lore in one step (turn 19), reaching 13.","impact":"positive"},{"turn":21,"label":"Big lore swing (you)","evidence":"+6 lore in one step (turn 21), reaching 19.","impact":"positive"},{"turn":null,"label":"Combo: dale","evidence":"Combo flag \"dale\" fired.","impact":"positive"}],"coach":{"headline":"Win via Combo payoff","summary":"You beat Sapphire/Steel Control at 20-6. Combo flag \"tripleShot\" fired and you closed the game.","whatWorked":["Combo flag \"tripleShot\" fired and you closed the game."],"whatFailed":[],"nextGameFocus":["Keep repeating this line — it matched your saved strategy."],"mulliganAdvice":"You mulliganed heavily this game — consider keeping slightly looser hands if this keeps happening.","matchupAdvice":"Against control, bait removal with mid-value bodies before committing your best threats; preserve a second wave.","deckImprovementIdeas":[],"confidence":0.7},"isDuplicateOfId":null,"oppInks":["Amethyst","Ruby"]},{"id":"g4ysrw1m","dateAdded":"2026-07-10","me":1,"onPlay":true,"mulligan":4,"myLore":2,"oppLore":2,"margin":0,"cross10":null,"cross20":null,"cross10MyTurn":null,"firstQuest":11,"firstQuestMyTurn":6,"myTurns":6,"gameTurns":12,"lorePerTurn":0.33,"result":"W","method":"concession","removedByMe":5,"myLost":2,"questers":{"Dale - Ready for His Shot":2},"combos":{},"loreByTurn":{"11":2},"oppLoreByTurn":{"10":2},"oppCards":["Akood et Emuti","Angel - Experiment 624","Angel - Siren Singer","Beyond the Horizon","Gigi - Best in Snow","Grand Councilwoman - Federation Leader","Lilo - Rock Star","Pleakley - Arctic Naturalist","Stitch - High Badness Level"],"archetype":"Amber/Steel","winCat":"Dale + Mulan board clear","lossCat":"","venue":"","notes":"","parserVersion":2,"rawHash":"8e831b3b5fe31b291ddc","planScore":{"score":65,"label":"Partly on plan","reasons":["Won, but by a thin margin — plan execution could be tighter."]},"winCondition":{"primary":"Opponent conceded behind","secondary":"","evidence":["Opponent conceded at 2 lore while you were at 2."],"confidence":0.85},"lossCondition":{"primary":"","secondary":"","evidence":[],"confidence":0},"keyTurningPoints":[{"turn":11,"label":"First quest","evidence":"Your first quest landed on turn 11 (your turn 6).","impact":"positive"},{"turn":null,"label":"Combo: dale","evidence":"Combo flag \"dale\" fired.","impact":"positive"},{"turn":null,"label":"Combo: mulanElite","evidence":"Combo flag \"mulanElite\" fired.","impact":"positive"},{"turn":null,"label":"Combo: tripleShot","evidence":"Combo flag \"tripleShot\" fired.","impact":"positive"},{"turn":null,"label":"Combo: reuben","evidence":"Combo flag \"reuben\" fired.","impact":"positive"},{"turn":null,"label":"Heavy removal","evidence":"Removed 5 opposing bodies.","impact":"positive"}],"coach":{"headline":"Win via Opponent conceded behind","summary":"You beat Other / Unknown at 2-2. Opponent conceded at 2 lore while you were at 2.","whatWorked":["Opponent conceded at 2 lore while you were at 2."],"whatFailed":["Won, but off the plan's own targets — see plan score reasons."],"nextGameFocus":["Tighten execution toward your saved strategy's turn targets next game."],"mulliganAdvice":"You mulliganed heavily this game — consider keeping slightly looser hands if this keeps happening.","matchupAdvice":"Log a few more games against this archetype to build a specific read.","deckImprovementIdeas":[],"confidence":0.75},"isDuplicateOfId":null,"oppInks":["Amber","Steel"]},{"id":"gtlrs3ja","dateAdded":"2026-07-10","me":2,"onPlay":false,"mulligan":5,"myLore":8,"oppLore":8,"margin":0,"cross10":null,"cross20":null,"cross10MyTurn":null,"firstQuest":8,"firstQuestMyTurn":4,"myTurns":9,"gameTurns":19,"lorePerTurn":0.89,"result":"W","method":"concession","removedByMe":7,"myLost":4,"questers":{"Gaston - Frightful Bully":1,"Dale - Ready for His Shot":6,"Chip - Retrieval Expert":1},"combos":{},"loreByTurn":{"8":1,"14":3,"16":5,"18":8},"oppLoreByTurn":{"3":1,"5":2,"7":4,"9":6,"17":8},"oppCards":["But I'm Much Faster","Inner Strength","Leviathan's Lair - Dangerous Ground","Maui - Half-Shark","Medallion Weights","Mr. Incredible - Bob Parr","Mr. Incredible - Super Strong","Mushu - Majestic Dragon","Next Stop","Olympus","One Last Hope","Raya - Headstrong","Robin Hood - Capable Fighter","Robin Hood - Champion of Sherwood"],"archetype":"Locations","winCat":"Dale + Mulan board clear","lossCat":"","venue":"","notes":"","parserVersion":2,"rawHash":"39e95098fa932b6a32ea","planScore":{"score":65,"label":"Partly on plan","reasons":["Won, but by a thin margin — plan execution could be tighter."]},"winCondition":{"primary":"Opponent conceded behind","secondary":"","evidence":["Opponent conceded at 8 lore while you were at 8."],"confidence":0.85},"lossCondition":{"primary":"","secondary":"","evidence":[],"confidence":0},"keyTurningPoints":[{"turn":8,"label":"First quest","evidence":"Your first quest landed on turn 8 (your turn 4).","impact":"positive"},{"turn":null,"label":"Combo: dale","evidence":"Combo flag \"dale\" fired.","impact":"positive"},{"turn":null,"label":"Combo: mulanElite","evidence":"Combo flag \"mulanElite\" fired.","impact":"positive"},{"turn":null,"label":"Combo: tripleShot","evidence":"Combo flag \"tripleShot\" fired.","impact":"positive"},{"turn":null,"label":"Combo: ohana","evidence":"Combo flag \"ohana\" fired.","impact":"positive"},{"turn":null,"label":"Combo: boost","evidence":"Combo flag \"boost\" fired.","impact":"positive"}],"coach":{"headline":"Win via Opponent conceded behind","summary":"You beat Locations at 8-8. Opponent conceded at 8 lore while you were at 8.","whatWorked":["Opponent conceded at 8 lore while you were at 8."],"whatFailed":["Won, but off the plan's own targets — see plan score reasons."],"nextGameFocus":["Tighten execution toward your saved strategy's turn targets next game."],"mulliganAdvice":"You mulliganed heavily this game — consider keeping slightly looser hands if this keeps happening.","matchupAdvice":"Against Locations, pressure the location-support characters early or race harder — locations don't trade in combat.","deckImprovementIdeas":[],"confidence":0.75},"isDuplicateOfId":null,"oppInks":["Ruby"]}],"duukay0":[]},"lib":[{"id":"d9g4yo6","title":"Every Story Needs a Hero!","inks":["ruby","amethyst"],"arch":"Ruby/Amethyst Super midrange — evasive pressure, damage control, and big challenge turns","tagline":"Slippery magic buys time until the Supers hit back.","cards":["4 Dumbo - Ninth Wonder of the Universe","4 Demona - Scourge of the Wyvern Clan","3 Hades - Looking for a Deal","4 Junior Woodchuck Guidebook","2 Hercules - Mighty Leader","4 Cheshire Cat - Inexplicable","4 Isis Vanderchill - Ice Queen of St. Canard","4 Scrooge McDuck - Ghostly Ebenezer","3 Elisa Maza - Transformed Gargoyle","2 Violet Parr - Learning New Powers","2 Frozone - Super Cool","4 Mr. Incredible - Super Strong","4 Frozone - Super Slick","4 Mrs. Incredible - Super Stretchy","4 Mr. Incredible - Bob Parr","2 Genie - Hard to Grasp","2 Peter Pan & Tinker Bell - Fast Friends","4 Luisa Madrigal - Pushing Through"],"mtime":"2026-07-11T01:30:33.883Z","heroArts":["Demona - Scourge of the Wyvern Clan","Peter Pan & Tinker Bell - Fast Friends","Dumbo - Ninth Wonder of the Universe"],"strategy":"Ruby/Amethyst tempo-control deck built to win by developing a stable board, denying the opponent’s best quests/challenges, then converting Evasive characters into card draw and lore through Dumbo - Ninth Wonder of the Universe.\n\nMain win plan: survive the early game, curve into efficient bodies, then stick Dumbo. Dumbo is the engine: he is Evasive, can exert/pay 1 to draw a card and gain 1 lore, and gives that same ability to other Evasive characters. Frozone - Super Slick, Violet Parr, and Mrs. Incredible become very important because they let the deck gain lore while drawing cards instead of running out of gas. Use Dumbo turns to snowball: every extra card drawn should either keep the board full, find Hades/Demona, or protect the final lore push.\n\nMulligan: prioritize a clean curve. Keep Luisa, Scrooge, Frozone - Super Slick, Junior Woodchuck Guidebook, Cheshire Cat, Violet, Dumbo, and one strong 4-cost play. Do not keep too many 5-6 cost cards unless the rest of the hand already plays smoothly. Junior Woodchuck Guidebook is excellent when the hand needs fuel, but do not spend tempo cracking it too early unless you are missing plays or need to refill.\n\nEarly game: play bodies, ink every turn, and avoid falling behind on board. Luisa and Bob Parr are early board presence. Scrooge McDuck - Ghostly Ebenezer can grow with Boost and become hard to trade into. Frozone - Super Slick is a premium early play because Evasive makes him a future Dumbo target. Against aggro, challenge only when it protects your lore race or prevents too much opponent lore. Against control, pressure early and force them to answer small threats before Dumbo arrives.\n\nMid game: shift from board building into board control. Cheshire Cat is one of the best tempo tools: Boost him to move damage from your characters onto opposing characters, turning damaged survivors into removal pressure. Isis Vanderchill and Frozone - Super Cool exert opposing characters so your board can quest safely or stop key opposing questers. Hades is your pressure valve: choose an opposing character and either the opponent bottoms it or you draw 2 cards. Both outcomes are good, so use Hades on characters the opponent really wants to keep.\n\nDumbo plan: once Dumbo is in play, every Evasive character becomes a mini-engine. If an Evasive character only quests for 1, using Dumbo’s granted ability is usually better because you still gain 1 lore and also draw a card. If Mrs. Incredible is gaining extra lore for the turn, decide between racing with questing or drawing with Dumbo based on whether you need cards or immediate lore. Do not expose Dumbo unnecessarily; he is the deck’s best way to beat control and long games.\n\nDemona plan: Demona is both comeback tool and finisher. When played, she exerts all opposing characters and refills players with fewer than 3 cards up to 3. Use her when the opponent has a board that would otherwise race or challenge you, or when exerting everything lets you swing the game with safe quests. Because of Stone By Day, manage your hand count carefully; if you have 3 or more cards, Demona will not ready. She is strongest when you are low on cards, ready to refill, and ready to close the game.\n\nHercules plan: Hercules protects himself from damage unless challenged, and while exerted he protects your other Hero characters from non-challenge damage. Use him against decks that rely on damage effects instead of normal challenges. He is especially important for keeping your Super/Hero board alive while you set up Dumbo and Demona turns.\n\nClosing the game: win by building a wide Evasive/Super board, drawing extra cards with Dumbo, then using Isis, Frozone - Super Cool, Hades, and Demona to remove or exert blockers. The final push often comes from a Demona turn that freezes the opposing board, followed by Evasive characters gaining lore safely while Dumbo keeps cards flowing.\n\nCommon mistakes to avoid: do not ink all your draw; do not play Dumbo into obvious removal without getting value; do not use every character only to challenge when you are supposed to be racing; do not overdraw with Demona if it stops her from readying next turn; do not forget that Dumbo’s granted ability can be better than normal questing on 1-lore Evasive characters.\n\nLoss conditions: the deck loses when it misses early ink, falls too far behind before Dumbo, lets aggro quest freely, or holds too many expensive cards without stabilizing. It also loses when Dumbo is removed before producing value and the hand runs empty. The main discipline is to keep a playable curve, protect the board, and only switch into full control mode when it buys real lore advantage."},{"id":"dmclck9","title":"Dale’s Growing Pressure!","inks":["amber","ruby"],"arch":"Amber/Ruby Dale Pressure Midrange -  damaged-character value, high-willpower challenges, and relentless board pressure.","tagline":"Turn damage into value, then let Dale make every challenge unfair.","strategy":"Amber/Ruby Dale Pressure deck built to win by creating early board presence, turning self-damaged characters into card advantage, then using Dale - Ready for His Shot to make high-willpower characters dominate challenges and clear the opponent’s board.\n\nMain win plan: develop a board faster than the opponent, pressure lore every turn, and force bad challenges. The deck becomes much stronger once Dale is in play because your characters deal challenge damage with their willpower instead of their strength. This turns characters like Mulan - Elite Archer, Zeus - Defiant God, Scrooge McDuck - Ghostly Ebenezer, Chip - Retrieval Expert, Bambi - Ethereal Fawn, and even Dale himself into dangerous board-control pieces. Your opponent should feel like every challenge against you is bad.\n\nMulligan: look for a playable curve and at least one value engine. Keep Mulan - Injured Soldier, Reuben - Sandwich Expert, Grandmother Willow, Webby’s Diary, Dale, Chip, Scrooge, Bambi, Ohana Means Family, and This Growing Pressure. Do not keep too many expensive cards unless your early plays are already solved. Mulan - Injured Soldier plus Reuben or Ohana is one of the best starts because it turns her starting damage into tempo or cards.\n\nEarly game: play Mulan - Injured Soldier aggressively. She starts damaged, but that is not a weakness in this deck; it enables Reuben and Ohana. Reuben can remove damage and discount your next character, helping you double-spell or play above curve. Ohana Means Family can turn damaged characters into a big refill, especially on Zeus or Mulan. Grandmother Willow helps smooth awkward hands by making your next character cheaper.\n\nMid game: establish Dale and start controlling combat. Once Dale is active, challenge math changes completely. High-willpower characters become removal tools. Chip is especially important because he can return a character with 4 or more willpower from discard and also gives Dale +1 willpower, making Dale harder to remove and stronger in challenges. Protect Dale whenever possible because he is the card that makes the whole deck unfair.\n\nMulan plan: Mulan - Injured Soldier is both an early play and the shift target for Mulan - Elite Archer. Shift Mulan - Elite Archer when you need to swing board control. With Dale in play, Mulan can deal damage based on her willpower during challenges, which makes her Triple Shot effect much more threatening. Without Dale, Medallion Weights can still boost her strength and let her challenge while drawing cards. Do not waste Mulan into a small target unless the extra damage clears important opposing characters.\n\nDamage package: Zeus - Defiant God and Mulan - Injured Soldier enter damaged, which sets up Ohana Means Family and Reuben. Ohana is your biggest comeback and refill card: use it when you can remove multiple damage and draw multiple cards, not just to heal 1. Reuben is tempo: use him to heal and immediately reduce the next character you play. The ideal turn is heal damage, draw or discount, then add another strong body.\n\nBoost package: Scrooge McDuck, Bambi, and Gaston all care about cards being placed under characters. Webby’s Diary rewards this plan by letting you pay 1 to draw whenever a card goes under one of your characters or locations. Bambi can become a major draw engine after Boosting because whenever he exerts during your turn, he reveals cards based on the number of cards under him and adds character cards to your hand. Scrooge grows bigger with each card under him and becomes especially dangerous with Dale because his willpower rises too.\n\nPressure tools: This Growing Pressure and Gaston force opposing characters into awkward lines by stopping them from challenging and making them quest if able. Use these effects on the opponent’s best challenger, bodyguard, or high-lore threat. The goal is to make them expose characters so your Dale-powered board can clean them up.\n\nRemoval tools: The Horseman Strikes! is your clean answer to Evasive characters and replaces itself by drawing a card. Medallion Weights turns a key challenge into card draw and can help Mulan or another attacker clear larger targets. Raging Storm is your panic button. Do not fire it just because you are slightly behind; use it when the opponent has committed more board than you, when you can rebuild faster, or when you have Chip/Ohana/Bambi/Webby’s Diary ready to recover.\n\nClosing the game: after you gain board control, stop over-challenging and start questing. This deck can accidentally play too much control and forget to win. Dale helps you win challenges, but the goal is still 20 lore. Once the opponent’s board is weak, use Gaston and This Growing Pressure to stop their best comeback challenge, then quest with your wide board. If they rebuild, punish them with Mulan, Medallion Weights, or Raging Storm.\n\nCommon mistakes to avoid: do not ink all your Ohana copies; do not play Dale without a plan to protect or use him; do not waste Ohana for only 1 card unless desperate; do not forget Webby’s Diary triggers when you Boost; do not use Raging Storm when you are the one ahead; do not tunnel on challenges when you can simply race to 20 lore.\n\nLoss conditions: the deck loses when it misses early ink, draws too many expensive cards without Reuben/Willow support, loses Dale before getting combat value, or wastes its healing/draw too early. It also struggles if the opponent removes your board before Ohana or Bambi can refill. The discipline is to curve out, turn damage into advantage, protect Dale, and only shift into full control when it creates a clear lore advantage.","cards":["4 Dale - Ready for His Shot","4 Mulan - Injured Soldier","4 Mulan - Elite Archer","4 Reuben - Sandwich Expert","4 Chip - Retrieval Expert","4 Stitch - Carefree Snowboarder","2 Stitch - Carefree Surfer","4 Gaston - Frightful Bully","4 Scrooge McDuck - Ghostly Ebenezer","4 Bambi - Ethereal Fawn","4 Zeus - Defiant God","4 Ohana Means Family","4 This Growing Pressure","3 The Horseman Strikes!","4 Webby's Diary","3 Medallion Weights","2 Grandmother Willow - Ancient Advisor","2 Raging Storm"],"mtime":"2026-07-10T21:49:28.664Z","heroArts":["Scrooge McDuck - Ghostly Ebenezer","Dale - Ready for His Shot","Mulan - Elite Archer"]},{"id":"duukay0","title":"Boostie Boys","inks":["amber","ruby"],"arch":"Location-control midrange — use removal and tempo tools to slow the opponent, build value through Scrooge’s Counting House, then close with big threats like Maleficent, Sulley & Boo, Hercules, and repeated board pressure.","tagline":"Freeze the board, build the bank, finish with monsters.","strategy":"This version is more proactive and location-focused than the previous list. You are not relying as much on healing/value from Ohana Means Family or Agustin, so you need to be cleaner with your removal and board sequencing.\n\nEarly game, look for Webby’s Diary, Scrooge McDuck, Liquidator - Iced Over, Raging Storm, and Scrooge’s Counting House. Your goal is to stop fast decks from snowballing while setting up a value engine.\n\nMidgame, the deck wants to control the pace with Aladdin - Barreling Through, The Horseman Strikes!, Red Alert, Gaston - Superior Archer, and Liquidator. You are trying to make the opponent’s characters awkward: damaged, frozen, removed, or forced into bad trades.\n\nYour main pressure package is Scrooge’s Counting House + Scrooge McDuck + Sulley/Boo package. Besties, Assemble!, Boo - Energetic Child, and Sulley & Boo - Scare Buddies suggest the deck wants a stronger character-synergy/value plan instead of pure removal control.\n\nLate game, Maleficent - Monstrous Dragon is your reset/finisher. After you clear the opponent’s best threat, you pivot into lore with your surviving board and locations.\n\nMain weakness: this list may be less forgiving because it has less healing and fewer recovery tools. If you fall behind too early, you need your removal to be precise. But if you stabilize, this version should close better with stronger board pressure.","cards":["4 Maleficent - Monstrous Dragon","1 Medallion Weights","2 Ariel - Ethereal Voice","4 Della's Moon Lullaby","4 Webby's Diary","4 Aladdin - Barreling Through","3 The Horseman Strikes!","4 Hercules - Spectral Demigod","4 Liquidator - Iced Over","4 Scrooge's Counting House - Ebenezer's Office","4 Raging Storm","4 Scrooge McDuck - Ghostly Ebenezer","3 Sulley - The New Boss","4 Sulley & Boo - Scare Buddies","4 Besties, Assemble!","3 Boo - Energetic Child","2 Red Alert","2 Gaston - Superior Archer"],"mtime":"2026-07-12T03:00:03.757Z","heroArts":["Gaston - Superior Archer","Sulley & Boo - Scare Buddies","Boo - Energetic Child"]}],"collection":{"elisa maza - transformed gargoyle":{"name":"Elisa Maza - Transformed Gargoyle","qty":3,"foil":0,"color":"Ruby","rarity":"Rare","set":"011","num":112},"junior woodchuck guidebook":{"name":"Junior Woodchuck Guidebook","qty":4,"foil":0,"color":"Amethyst","rarity":"Common","set":"010","num":66},"hades - looking for a deal":{"name":"Hades - Looking for a Deal","qty":1,"foil":0,"color":"Amethyst","rarity":"Legendary","set":"010","num":56},"nani - stage manager":{"name":"Nani - Stage Manager","qty":4,"foil":0,"color":"Amber","rarity":"Uncommon","set":"011","num":20},"pedro madrigal - family patriarch":{"name":"Pedro Madrigal - Family Patriarch","qty":10,"foil":1,"color":"Amber","rarity":"Uncommon","set":"012","num":5},"alan-a-dale - loyal bard":{"name":"Alan-a-Dale - Loyal Bard","qty":11,"foil":0,"color":"Amber","rarity":"Common","set":"012","num":7},"hamm - piggy bank":{"name":"Hamm - Piggy Bank","qty":9,"foil":0,"color":"Amber","rarity":"Uncommon","set":"012","num":11},"monterey jack - hypnotized by cheese":{"name":"Monterey Jack - Hypnotized by Cheese","qty":4,"foil":1,"color":"Amber","rarity":"Rare","set":"012","num":12},"dale - excited friend":{"name":"Dale - Excited Friend","qty":11,"foil":0,"color":"Amber","rarity":"Common","set":"012","num":4},"gosalyn mallard - the quiverwing quack":{"name":"Gosalyn Mallard - The Quiverwing Quack","qty":12,"foil":1,"color":"Amber","rarity":"Common","set":"012","num":1},"pluto - vigilant traveler":{"name":"Pluto - Vigilant Traveler","qty":6,"foil":0,"color":"Amber","rarity":"Uncommon","set":"012","num":25},"ranger team-up":{"name":"Ranger Team-Up","qty":4,"foil":0,"color":"Amber","rarity":"Uncommon","set":"012","num":28},"bo peep - caring shepherd":{"name":"Bo Peep - Caring Shepherd","qty":7,"foil":0,"color":"Amber","rarity":"Uncommon","set":"012","num":13},"bullseye - loyal horse":{"name":"Bullseye - Loyal Horse","qty":12,"foil":0,"color":"Amber","rarity":"Common","set":"012","num":17},"when you need help, just call":{"name":"When You Need Help, Just Call","qty":6,"foil":2,"color":"Amber","rarity":"Rare","set":"012","num":32},"woody - waiting for a friend":{"name":"Woody - Waiting for a Friend","qty":12,"foil":1,"color":"Amber","rarity":"Common","set":"012","num":3},"julieta madrigal - caring baker":{"name":"Julieta Madrigal - Caring Baker","qty":13,"foil":1,"color":"Amber","rarity":"Common","set":"012","num":24},"isabela madrigal - such a lovely voice":{"name":"Isabela Madrigal - Such a Lovely Voice","qty":10,"foil":1,"color":"Amber","rarity":"Epic","set":"012","num":207},"the prince - searching for his love":{"name":"The Prince - Searching for His Love","qty":4,"foil":1,"color":"Amber","rarity":"Rare","set":"012","num":23},"andy's room - home base":{"name":"Andy's Room - Home Base","qty":6,"foil":0,"color":"Amber","rarity":"Rare","set":"012","num":34},"dale - ready for his shot":{"name":"Dale - Ready for His Shot","qty":5,"foil":1,"color":"Amber","rarity":"Legendary","set":"012","num":22},"agustin madrigal - exceptionally kind":{"name":"Agustin Madrigal - Exceptionally Kind","qty":8,"foil":0,"color":"Amber","rarity":"Common","set":"012","num":6},"ariel - curious traveler":{"name":"Ariel - Curious Traveler","qty":2,"foil":0,"color":"Amber","rarity":"Rare","set":"012","num":18},"safety rope":{"name":"Safety Rope","qty":12,"foil":1,"color":"Amber","rarity":"Uncommon","set":"012","num":33},"monterey jack - watchful ranger":{"name":"Monterey Jack - Watchful Ranger","qty":16,"foil":4,"color":"Amber","rarity":"Common","set":"012","num":2},"this growing pressure":{"name":"This Growing Pressure","qty":9,"foil":0,"color":"Amber","rarity":"Common","set":"012","num":29},"metamorphosis":{"name":"Metamorphosis","qty":3,"foil":0,"color":"Amber","rarity":"Rare","set":"012","num":31},"chip - retrieval expert":{"name":"Chip - Retrieval Expert","qty":5,"foil":0,"color":"Amber","rarity":"Uncommon","set":"012","num":14},"dolores madrigal - hears everything":{"name":"Dolores Madrigal - Hears Everything","qty":9,"foil":0,"color":"Amber","rarity":"Common","set":"012","num":9},"prince eric - noble swordsman":{"name":"Prince Eric - Noble Swordsman","qty":11,"foil":1,"color":"Amber","rarity":"Common","set":"012","num":8},"isabela madrigal - caring cultivator":{"name":"Isabela Madrigal - Caring Cultivator","qty":5,"foil":1,"color":"Amber","rarity":"Rare","set":"012","num":19},"doc - taking notes":{"name":"Doc - Taking Notes","qty":14,"foil":3,"color":"Amethyst","rarity":"Epic","set":"012","num":210},"luisa madrigal - pushing through":{"name":"Luisa Madrigal - Pushing Through","qty":12,"foil":1,"color":"Amethyst","rarity":"Common","set":"012","num":62},"mor'du - wicked with pride":{"name":"Mor'du - Wicked with Pride","qty":11,"foil":1,"color":"Amethyst","rarity":"Common","set":"012","num":35},"alma madrigal - leading the way":{"name":"Alma Madrigal - Leading the Way","qty":9,"foil":0,"color":"Amethyst","rarity":"Uncommon","set":"012","num":36},"happy - joyful adventurer":{"name":"Happy - Joyful Adventurer","qty":12,"foil":0,"color":"Amethyst","rarity":"Common","set":"012","num":43},"alma madrigal - heart of the family":{"name":"Alma Madrigal - Heart of the Family","qty":11,"foil":0,"color":"Amethyst","rarity":"Common","set":"012","num":45},"mickey mouse - expedition leader":{"name":"Mickey Mouse - Expedition Leader","qty":3,"foil":0,"color":"Amber","rarity":"Super Rare","set":"012","num":26},"luisa madrigal - confident climber":{"name":"Luisa Madrigal - Confident Climber","qty":2,"foil":0,"color":"Amethyst","rarity":"Legendary","set":"012","num":60},"ring of stones - place of legends":{"name":"Ring of Stones - Place of Legends","qty":4,"foil":0,"color":"Amethyst","rarity":"Rare","set":"012","num":68},"sleepy - deep sleeper":{"name":"Sleepy - Deep Sleeper","qty":14,"foil":1,"color":"Amethyst","rarity":"Common","set":"012","num":44},"frozone - super slick":{"name":"Frozone - Super Slick","qty":10,"foil":0,"color":"Amethyst","rarity":"Common","set":"012","num":46},"violet parr - learning new powers":{"name":"Violet Parr - Learning New Powers","qty":8,"foil":2,"color":"Amethyst","rarity":"Uncommon","set":"012","num":48},"edna mode - fashion designer":{"name":"Edna Mode - Fashion Designer","qty":4,"foil":1,"color":"Amethyst","rarity":"Rare","set":"012","num":54},"right behind you":{"name":"Right Behind You","qty":8,"foil":0,"color":"Amethyst","rarity":"Uncommon","set":"012","num":64},"chip - team player":{"name":"Chip - Team Player","qty":12,"foil":1,"color":"Amber","rarity":"Common","set":"012","num":27},"snow white - merry as the morning":{"name":"Snow White - Merry as the Morning","qty":2,"foil":0,"color":"Amethyst","rarity":"Legendary","set":"012","num":37},"will o' the wisp - forest spirit":{"name":"Will o' the Wisp - Forest Spirit","qty":15,"foil":1,"color":"Amethyst","rarity":"Common","set":"012","num":47},"super suit":{"name":"Super Suit","qty":6,"foil":0,"color":"Amethyst","rarity":"Uncommon","set":"012","num":66},"dunbroch family tapestry":{"name":"DunBroch Family Tapestry","qty":2,"foil":0,"color":"Amethyst","rarity":"Rare","set":"012","num":67},"sneezy - startlingly loud":{"name":"Sneezy - Startlingly Loud","qty":13,"foil":1,"color":"Amethyst","rarity":"Common","set":"012","num":42},"hamish, hubert & harris - making mischief":{"name":"Hamish, Hubert & Harris - Making Mischief","qty":4,"foil":0,"color":"Amethyst","rarity":"Uncommon","set":"012","num":50},"elinor - bespelled queen":{"name":"Elinor - Bespelled Queen","qty":9,"foil":1,"color":"Amethyst","rarity":"Uncommon","set":"012","num":51},"mickey mouse - experienced traveler":{"name":"Mickey Mouse - Experienced Traveler","qty":7,"foil":2,"color":"Amethyst","rarity":"Uncommon","set":"012","num":52},"pepa madrigal - calm before the storm":{"name":"Pepa Madrigal - Calm Before the Storm","qty":3,"foil":0,"color":"Amethyst","rarity":"Super Rare","set":"012","num":56},"mirage - super recruiter":{"name":"Mirage - Super Recruiter","qty":11,"foil":2,"color":"Amethyst","rarity":"Common","set":"012","num":53},"dash parr - lava runner":{"name":"Dash Parr - Lava Runner","qty":5,"foil":1,"color":"Amethyst","rarity":"Super Rare","set":"012","num":61},"super relocation program":{"name":"Super Relocation Program","qty":10,"foil":1,"color":"Amethyst","rarity":"Common","set":"012","num":63},"mrs. incredible - super stretchy":{"name":"Mrs. Incredible - Super Stretchy","qty":4,"foil":0,"color":"Amethyst","rarity":"Rare","set":"012","num":49},"maleficent - imperious traveler":{"name":"Maleficent - Imperious Traveler","qty":3,"foil":0,"color":"Amethyst","rarity":"Rare","set":"012","num":55},"mor'du - savage cursed prince":{"name":"Mor'du - Savage Cursed Prince","qty":4,"foil":1,"color":"Amethyst","rarity":"Super Rare","set":"012","num":57},"don't be nervous":{"name":"Don't Be Nervous","qty":6,"foil":0,"color":"Amethyst","rarity":"Rare","set":"012","num":65},"dopey - drawn to music":{"name":"Dopey - Drawn to Music","qty":7,"foil":0,"color":"Amethyst","rarity":"Uncommon","set":"012","num":38},"frozone - super cool":{"name":"Frozone - Super Cool","qty":5,"foil":1,"color":"Amethyst","rarity":"Rare","set":"012","num":59},"grumpy - soreheaded miner":{"name":"Grumpy - Soreheaded Miner","qty":11,"foil":2,"color":"Amethyst","rarity":"Common","set":"012","num":41},"merida - defiant daughter":{"name":"Merida - Defiant Daughter","qty":16,"foil":3,"color":"Emerald","rarity":"Common","set":"012","num":69},"young macguffin - soft-spoken son":{"name":"Young MacGuffin - Soft-Spoken Son","qty":9,"foil":0,"color":"Emerald","rarity":"Common","set":"012","num":71},"buzz lightyear - space ranger":{"name":"Buzz Lightyear - Space Ranger","qty":9,"foil":0,"color":"Emerald","rarity":"Common","set":"012","num":76},"merida's bow":{"name":"Merida's Bow","qty":14,"foil":1,"color":"Emerald","rarity":"Common","set":"012","num":101},"lyle tiberius rourke - adventurer for hire":{"name":"Lyle Tiberius Rourke - Adventurer for Hire","qty":8,"foil":1,"color":"Emerald","rarity":"Uncommon","set":"012","num":87},"buzz's arm":{"name":"Buzz's Arm","qty":6,"foil":0,"color":"Emerald","rarity":"Uncommon","set":"012","num":98},"lenny - toy binoculars":{"name":"Lenny - Toy Binoculars","qty":5,"foil":1,"color":"Emerald","rarity":"Rare","set":"012","num":79},"sabotage":{"name":"Sabotage","qty":11,"foil":0,"color":"Emerald","rarity":"Common","set":"012","num":96},"bashful - riding the rails":{"name":"Bashful - Riding the Rails","qty":12,"foil":1,"color":"Amethyst","rarity":"Common","set":"012","num":39},"gaetan moliere - clever burrower":{"name":"Gaetan Moliere - Clever Burrower","qty":8,"foil":4,"color":"Emerald","rarity":"Uncommon","set":"012","num":80},"alma madrigal - keeper of the flame":{"name":"Alma Madrigal - Keeper of the Flame","qty":4,"foil":1,"color":"Amethyst","rarity":"Rare","set":"012","num":58},"the queen - evil ruler":{"name":"The Queen - Evil Ruler","qty":12,"foil":0,"color":"Emerald","rarity":"Common","set":"012","num":75},"rc - remote-controlled car":{"name":"RC - Remote-Controlled Car","qty":10,"foil":0,"color":"Emerald","rarity":"Common","set":"012","num":77},"alien - true believer":{"name":"Alien - True Believer","qty":5,"foil":1,"color":"Emerald","rarity":"Rare","set":"012","num":83},"joshua sweet - field surgeon":{"name":"Joshua Sweet - Field Surgeon","qty":11,"foil":1,"color":"Emerald","rarity":"Common","set":"012","num":88},"hamish, hubert & harris - troublemaking triplets":{"name":"Hamish, Hubert & Harris - Troublemaking Triplets","qty":11,"foil":0,"color":"Emerald","rarity":"Common","set":"012","num":70},"peter pan - searching far and wide":{"name":"Peter Pan - Searching Far and Wide","qty":10,"foil":1,"color":"Emerald","rarity":"Uncommon","set":"012","num":81},"the huntsman - on the queen's orders":{"name":"The Huntsman - On the Queen's Orders","qty":4,"foil":0,"color":"Emerald","rarity":"Uncommon","set":"012","num":94},"gyro-evac":{"name":"Gyro-Evac","qty":12,"foil":1,"color":"Emerald","rarity":"Uncommon","set":"012","num":100},"helga sinclair - no backup needed":{"name":"Helga Sinclair - No Backup Needed","qty":10,"foil":0,"color":"Emerald","rarity":"Common","set":"012","num":73},"elinor - renowned diplomat":{"name":"Elinor - Renowned Diplomat","qty":6,"foil":1,"color":"Emerald","rarity":"Super Rare","set":"012","num":86},"strange things":{"name":"Strange Things","qty":6,"foil":2,"color":"Emerald","rarity":"Uncommon","set":"012","num":95},"helga sinclair - prepared for anything":{"name":"Helga Sinclair - Prepared for Anything","qty":4,"foil":0,"color":"Emerald","rarity":"Rare","set":"012","num":93},"the family scattered":{"name":"The Family Scattered","qty":2,"foil":0,"color":"Emerald","rarity":"Super Rare","set":"012","num":97},"mr. incredible - bob parr":{"name":"Mr. Incredible - Bob Parr","qty":14,"foil":1,"color":"Ruby","rarity":"Common","set":"012","num":104},"audrey ramirez - gutsy mechanic":{"name":"Audrey Ramirez - Gutsy Mechanic","qty":12,"foil":0,"color":"Ruby","rarity":"Common","set":"012","num":107},"hand-in-the-box - sid's toy":{"name":"Hand-in-the-Box - Sid's Toy","qty":5,"foil":0,"color":"Ruby","rarity":"Uncommon","set":"012","num":114},"hero work":{"name":"Hero Work","qty":3,"foil":0,"color":"Ruby","rarity":"Rare","set":"012","num":132},"the witch - wily woodcarver":{"name":"The Witch - Wily Woodcarver","qty":11,"foil":0,"color":"Emerald","rarity":"Common","set":"012","num":74},"donald duck - distracted traveler":{"name":"Donald Duck - Distracted Traveler","qty":9,"foil":3,"color":"Emerald","rarity":"Uncommon","set":"012","num":84},"merida - gifted archer":{"name":"Merida - Gifted Archer","qty":3,"foil":0,"color":"Emerald","rarity":"Rare","set":"012","num":89},"milo thatch - getting his hands dirty":{"name":"Milo Thatch - Getting His Hands Dirty","qty":4,"foil":2,"color":"Emerald","rarity":"Super Rare","set":"012","num":82},"buzz lightyear - jungle ranger":{"name":"Buzz Lightyear - Jungle Ranger","qty":5,"foil":0,"color":"Emerald","rarity":"Legendary","set":"012","num":91},"the queen - devious disguise":{"name":"The Queen - Devious Disguise","qty":4,"foil":0,"color":"Emerald","rarity":"Legendary","set":"012","num":90},"jebidiah farnsworth - cookie":{"name":"Jebidiah Farnsworth - Cookie","qty":6,"foil":0,"color":"Ruby","rarity":"Uncommon","set":"012","num":117},"leviathan's lair - dangerous ground":{"name":"Leviathan's Lair - Dangerous Ground","qty":3,"foil":0,"color":"Ruby","rarity":"Rare","set":"012","num":136},"hercules - young rescuer":{"name":"Hercules - Young Rescuer","qty":4,"foil":1,"color":"Ruby","rarity":"Super Rare","set":"012","num":123},"pterodactyl janie doll - sid's toy":{"name":"Pterodactyl Janie Doll - Sid's Toy","qty":12,"foil":1,"color":"Ruby","rarity":"Common","set":"012","num":128},"jingle joe - sid's toy":{"name":"Jingle Joe - Sid's Toy","qty":10,"foil":0,"color":"Ruby","rarity":"Common","set":"012","num":111},"wind-up frog - sid's toy":{"name":"Wind-Up Frog - Sid's Toy","qty":14,"foil":2,"color":"Ruby","rarity":"Common","set":"012","num":112},"like a bird in the sky":{"name":"Like A Bird In the Sky","qty":12,"foil":1,"color":"Ruby","rarity":"Common","set":"012","num":131},"firefly swarm":{"name":"Firefly Swarm","qty":7,"foil":0,"color":"Ruby","rarity":"Uncommon","set":"012","num":130},"preston whitmore - expedition financier":{"name":"Preston Whitmore - Expedition Financier","qty":12,"foil":1,"color":"Ruby","rarity":"Common","set":"012","num":110},"pegasus - searching high and low":{"name":"Pegasus - Searching High and Low","qty":11,"foil":0,"color":"Ruby","rarity":"Common","set":"012","num":106},"tod - nimble fox":{"name":"Tod - Nimble Fox","qty":14,"foil":3,"color":"Emerald","rarity":"Common","set":"012","num":72},"cruella de vil - judgmental traveler":{"name":"Cruella De Vil - Judgmental Traveler","qty":4,"foil":0,"color":"Emerald","rarity":"Rare","set":"012","num":92},"remote inklands - desert ruins":{"name":"Remote Inklands - Desert Ruins","qty":4,"foil":0,"color":"Ruby","rarity":"Rare","set":"012","num":135},"amazu's inkcaster":{"name":"Amazu's Inkcaster","qty":7,"foil":1,"color":"Ruby","rarity":"Uncommon","set":"012","num":134},"inner strength":{"name":"Inner Strength","qty":10,"foil":0,"color":"Ruby","rarity":"Common","set":"012","num":129},"dangerous plan":{"name":"Dangerous Plan","qty":12,"foil":3,"color":"Ruby","rarity":"Common","set":"012","num":133},"milo thatch - courageous explorer":{"name":"Milo Thatch - Courageous Explorer","qty":11,"foil":1,"color":"Ruby","rarity":"Common","set":"012","num":108},"babyhead - leader of sid's toys":{"name":"Babyhead - Leader of Sid's Toys","qty":4,"foil":0,"color":"Ruby","rarity":"Rare","set":"012","num":119},"queen of hearts - impatient traveler":{"name":"Queen of Hearts - Impatient Traveler","qty":3,"foil":0,"color":"Ruby","rarity":"Rare","set":"012","num":122},"dash parr - super speedy":{"name":"Dash Parr - Super Speedy","qty":8,"foil":0,"color":"Ruby","rarity":"Uncommon","set":"012","num":118},"lyle tiberius rourke - crystallized commander":{"name":"Lyle Tiberius Rourke - Crystallized Commander","qty":6,"foil":3,"color":"Ruby","rarity":"Rare","set":"012","num":103},"lyle tiberius rourke - looking for his moment":{"name":"Lyle Tiberius Rourke - Looking for His Moment","qty":10,"foil":0,"color":"Ruby","rarity":"Common","set":"012","num":105},"roller bob - sid's toy":{"name":"Roller Bob - Sid's Toy","qty":12,"foil":0,"color":"Ruby","rarity":"Uncommon","set":"012","num":113},"kida - guardian of the path":{"name":"Kida - Guardian of the Path","qty":11,"foil":2,"color":"Sapphire","rarity":"Common","set":"012","num":144},"daisy duck - trendy traveler":{"name":"Daisy Duck - Trendy Traveler","qty":9,"foil":1,"color":"Ruby","rarity":"Uncommon","set":"012","num":115},"vincenzo santorini - on the run":{"name":"Vincenzo Santorini - On the Run","qty":3,"foil":0,"color":"Ruby","rarity":"Rare","set":"012","num":124},"jack-jack parr - incredible potential":{"name":"Jack-Jack Parr - Incredible Potential","qty":1,"foil":1,"color":"Ruby","rarity":"Super Rare","set":"012","num":121},"zeus - defiant god":{"name":"Zeus - Defiant God","qty":8,"foil":0,"color":"Ruby","rarity":"Uncommon","set":"012","num":109},"bouncing ducky - sid's toy":{"name":"Bouncing Ducky - Sid's Toy","qty":4,"foil":1,"color":"Ruby","rarity":"Rare","set":"012","num":120},"the leviathan - guardian of atlantis":{"name":"The Leviathan - Guardian of Atlantis","qty":4,"foil":1,"color":"Ruby","rarity":"Super Rare","set":"012","num":125},"sid phillips - toy surgeon":{"name":"Sid Phillips - Toy Surgeon","qty":6,"foil":1,"color":"Ruby","rarity":"Legendary","set":"012","num":126},"syndrome - evil inventor":{"name":"Syndrome - Evil Inventor","qty":12,"foil":0,"color":"Sapphire","rarity":"Common","set":"012","num":143},"copper - big dog":{"name":"Copper - Big Dog","qty":8,"foil":2,"color":"Ruby","rarity":"Uncommon","set":"012","num":116},"ursula - deal maker":{"name":"Ursula - Deal Maker","qty":4,"foil":0,"color":"Sapphire","rarity":"Legendary","set":"012","num":161},"kida - crystal scion":{"name":"Kida - Crystal Scion","qty":1,"foil":0,"color":"Sapphire","rarity":"Legendary","set":"012","num":160},"casa madrigal - courtyard":{"name":"Casa Madrigal - Courtyard","qty":9,"foil":0,"color":"Sapphire","rarity":"Common","set":"012","num":170},"robin hood - desert wanderer":{"name":"Robin Hood - Desert Wanderer","qty":10,"foil":0,"color":"Sapphire","rarity":"Common","set":"012","num":137},"fauna - good-natured fairy":{"name":"Fauna - Good-Natured Fairy","qty":9,"foil":0,"color":"Sapphire","rarity":"Common","set":"012","num":140},"zipper - tiny helper":{"name":"Zipper - Tiny Helper","qty":7,"foil":0,"color":"Sapphire","rarity":"Uncommon","set":"012","num":148},"minnie mouse - practical traveler":{"name":"Minnie Mouse - Practical Traveler","qty":11,"foil":2,"color":"Sapphire","rarity":"Uncommon","set":"012","num":159},"julieta's arepas":{"name":"Julieta's Arepas","qty":11,"foil":0,"color":"Sapphire","rarity":"Common","set":"012","num":166},"prince charming - searching for answers":{"name":"Prince Charming - Searching for Answers","qty":15,"foil":0,"color":"Sapphire","rarity":"Common","set":"012","num":138},"someone will lose his head":{"name":"Someone Will Lose His Head","qty":12,"foil":1,"color":"Sapphire","rarity":"Common","set":"012","num":162},"gadget hackwrench - finder of lost parts":{"name":"Gadget Hackwrench - Finder of Lost Parts","qty":12,"foil":2,"color":"Sapphire","rarity":"Common","set":"012","num":147},"edna mode - super suit designer":{"name":"Edna Mode - Super Suit Designer","qty":6,"foil":0,"color":"Sapphire","rarity":"Rare","set":"012","num":149},"shepherd's journal":{"name":"Shepherd's Journal","qty":5,"foil":0,"color":"Sapphire","rarity":"Uncommon","set":"012","num":169},"zipper - big helper":{"name":"Zipper - Big Helper","qty":4,"foil":0,"color":"Sapphire","rarity":"Super Rare","set":"012","num":150},"flora - strong-willed fairy":{"name":"Flora - Strong-Willed Fairy","qty":3,"foil":0,"color":"Sapphire","rarity":"Rare","set":"012","num":141},"bruno madrigal - oasis oracle":{"name":"Bruno Madrigal - Oasis Oracle","qty":3,"foil":1,"color":"Sapphire","rarity":"Rare","set":"012","num":154},"kashekim - wise king":{"name":"Kashekim - Wise King","qty":8,"foil":1,"color":"Sapphire","rarity":"Uncommon","set":"012","num":158},"isabela madrigal - perfectly in control":{"name":"Isabela Madrigal - Perfectly in Control","qty":2,"foil":0,"color":"Sapphire","rarity":"Super Rare","set":"012","num":153},"bruno madrigal - seeing the future":{"name":"Bruno Madrigal - Seeing the Future","qty":14,"foil":0,"color":"Sapphire","rarity":"Common","set":"012","num":156},"mr. incredible - super strong":{"name":"Mr. Incredible - Super Strong","qty":4,"foil":0,"color":"Ruby","rarity":"Legendary","set":"012","num":127},"salvage operation":{"name":"Salvage Operation","qty":9,"foil":2,"color":"Sapphire","rarity":"Uncommon","set":"012","num":165},"gadget's goggles":{"name":"Gadget's Goggles","qty":4,"foil":0,"color":"Sapphire","rarity":"Uncommon","set":"012","num":168},"ranger plane":{"name":"Ranger Plane","qty":4,"foil":0,"color":"Sapphire","rarity":"Rare","set":"012","num":167},"norton nimnul - misanthropic genius":{"name":"Norton Nimnul - Misanthropic Genius","qty":8,"foil":1,"color":"Sapphire","rarity":"Uncommon","set":"012","num":146},"dr. sara bellum - head of research":{"name":"Dr. Sara Bellum - Head of Research","qty":12,"foil":2,"color":"Sapphire","rarity":"Common","set":"012","num":152},"kida - discovering the unknown":{"name":"Kida - Discovering the Unknown","qty":4,"foil":1,"color":"Sapphire","rarity":"Rare","set":"012","num":157},"cinderella - resourceful traveler":{"name":"Cinderella - Resourceful Traveler","qty":6,"foil":3,"color":"Sapphire","rarity":"Rare","set":"012","num":155},"gadget hackwrench - resourceful mechanic":{"name":"Gadget Hackwrench - Resourceful Mechanic","qty":1,"foil":0,"color":"Sapphire","rarity":"Super Rare","set":"012","num":145},"what else can i do?":{"name":"What Else Can I Do?","qty":3,"foil":0,"color":"Sapphire","rarity":"Rare","set":"012","num":163},"escape plan":{"name":"Escape Plan","qty":6,"foil":0,"color":"Sapphire","rarity":"Rare","set":"012","num":164},"luisa madrigal - no pressure":{"name":"Luisa Madrigal - No Pressure","qty":6,"foil":0,"color":"Sapphire","rarity":"Uncommon","set":"012","num":151},"merryweather - feisty fairy":{"name":"Merryweather - Feisty Fairy","qty":11,"foil":1,"color":"Sapphire","rarity":"Uncommon","set":"012","num":139},"mirabel madrigal - resourceful daughter":{"name":"Mirabel Madrigal - Resourceful Daughter","qty":12,"foil":1,"color":"Sapphire","rarity":"Common","set":"012","num":142},"fat cat's club - seedy headquarters":{"name":"Fat Cat's Club - Seedy Headquarters","qty":11,"foil":0,"color":"Steel","rarity":"Common","set":"012","num":203},"the island of nomanisan - syndrome's headquarters":{"name":"The Island of Nomanisan - Syndrome's Headquarters","qty":5,"foil":1,"color":"Steel","rarity":"Rare","set":"012","num":204},"violet parr - at wits' end":{"name":"Violet Parr - At Wits' End","qty":11,"foil":0,"color":"Steel","rarity":"Common","set":"012","num":178},"syndrome - out for revenge":{"name":"Syndrome - Out for Revenge","qty":8,"foil":1,"color":"Steel","rarity":"Enchanted","set":"012","num":238},"fergus - king of dunbroch":{"name":"Fergus - King of DunBroch","qty":11,"foil":0,"color":"Steel","rarity":"Common","set":"012","num":175},"pocahontas - steadfast traveler":{"name":"Pocahontas - Steadfast Traveler","qty":7,"foil":4,"color":"Steel","rarity":"Rare","set":"012","num":171},"wee dingwall - scrappy lad":{"name":"Wee Dingwall - Scrappy Lad","qty":11,"foil":0,"color":"Steel","rarity":"Common","set":"012","num":176},"lord macintosh - wiry and high-strung":{"name":"Lord Macintosh - Wiry and High-Strung","qty":8,"foil":0,"color":"Steel","rarity":"Uncommon","set":"012","num":181},"merida - formidable archer":{"name":"Merida - Formidable Archer","qty":2,"foil":0,"color":"Steel","rarity":"Legendary","set":"012","num":191},"mrs. incredible - determined rescuer":{"name":"Mrs. Incredible - Determined Rescuer","qty":4,"foil":0,"color":"Steel","rarity":"Legendary","set":"012","num":195},"club door":{"name":"Club Door","qty":11,"foil":1,"color":"Steel","rarity":"Uncommon","set":"012","num":202},"omnidroid - v.8":{"name":"Omnidroid - V.8","qty":11,"foil":2,"color":"Steel","rarity":"Common","set":"012","num":173},"john smith - skillful explorer":{"name":"John Smith - Skillful Explorer","qty":5,"foil":0,"color":"Steel","rarity":"Rare","set":"012","num":192},"incrediboy - buddy pine":{"name":"Incrediboy - Buddy Pine","qty":13,"foil":1,"color":"Steel","rarity":"Common","set":"012","num":177},"goofy - determined traveler":{"name":"Goofy - Determined Traveler","qty":7,"foil":1,"color":"Steel","rarity":"Uncommon","set":"012","num":189},"three arrows":{"name":"Three Arrows","qty":6,"foil":0,"color":"Steel","rarity":"Uncommon","set":"012","num":197},"card advantage":{"name":"Card Advantage","qty":7,"foil":0,"color":"Steel","rarity":"Uncommon","set":"012","num":198},"angus - mighty horse":{"name":"Angus - Mighty Horse","qty":12,"foil":2,"color":"Steel","rarity":"Common","set":"012","num":174},"omnidroid - v.9":{"name":"Omnidroid - V.9","qty":11,"foil":1,"color":"Steel","rarity":"Uncommon","set":"012","num":184},"rat capone - rodent gangster":{"name":"Rat Capone - Rodent Gangster","qty":13,"foil":2,"color":"Steel","rarity":"Common","set":"012","num":183},"mr. incredible - taking out the trash":{"name":"Mr. Incredible - Taking Out the Trash","qty":5,"foil":0,"color":"Steel","rarity":"Uncommon","set":"012","num":185},"plunger crossbow":{"name":"Plunger Crossbow","qty":9,"foil":0,"color":"Steel","rarity":"Common","set":"012","num":200},"mrs. incredible - helen parr":{"name":"Mrs. Incredible - Helen Parr","qty":12,"foil":0,"color":"Steel","rarity":"Common","set":"012","num":179},"diablo - stone servant":{"name":"Diablo - Stone Servant","qty":2,"foil":1,"color":"Steel","rarity":"Super Rare","set":"012","num":196},"touch the sky":{"name":"Touch the Sky","qty":4,"foil":0,"color":"Steel","rarity":"Rare","set":"012","num":199},"syndrome's remote":{"name":"Syndrome's Remote","qty":4,"foil":1,"color":"Steel","rarity":"Rare","set":"012","num":201},"fergus - outpost builder":{"name":"Fergus - Outpost Builder","qty":4,"foil":0,"color":"Steel","rarity":"Super Rare","set":"012","num":194},"young macintosh - proud son":{"name":"Young Macintosh - Proud Son","qty":14,"foil":2,"color":"Steel","rarity":"Common","set":"012","num":180},"maudie - exasperated nursemaid":{"name":"Maudie - Exasperated Nursemaid","qty":9,"foil":0,"color":"Steel","rarity":"Uncommon","set":"012","num":188},"fat cat - criminal businessman":{"name":"Fat Cat - Criminal Businessman","qty":3,"foil":0,"color":"Steel","rarity":"Rare","set":"012","num":187},"lord dingwall - bullheaded":{"name":"Lord Dingwall - Bullheaded","qty":8,"foil":2,"color":"Steel","rarity":"Uncommon","set":"012","num":186},"gizmoduck - duckburg defender":{"name":"Gizmoduck - Duckburg Defender","qty":3,"foil":0,"color":"Steel","rarity":"Rare","set":"012","num":193},"fat cat - felonious feline":{"name":"Fat Cat - Felonious Feline","qty":10,"foil":0,"color":"Steel","rarity":"Common","set":"012","num":182},"omnidroid - v.10":{"name":"Omnidroid - V.10","qty":5,"foil":1,"color":"Steel","rarity":"Rare","set":"012","num":190},"jessie - lively cowgirl":{"name":"Jessie - Lively Cowgirl","qty":7,"foil":0,"color":"Amber","rarity":"Super Rare","set":"012","num":20},"woody - jungle guide":{"name":"Woody - Jungle Guide","qty":6,"foil":2,"color":"Amber","rarity":"Legendary","set":"012","num":15},"pizza planet - spaceport":{"name":"Pizza Planet - Spaceport","qty":5,"foil":0,"color":"Emerald","rarity":"Rare","set":"012","num":102},"the claw":{"name":"The Claw","qty":5,"foil":0,"color":"Emerald","rarity":"Rare","set":"012","num":99},"buzz lightyear - on the way":{"name":"Buzz Lightyear - On the Way","qty":3,"foil":0,"color":"Emerald","rarity":"Rare","set":"012","num":85},"enigmatic inkcaster":{"name":"Enigmatic Inkcaster","qty":4,"foil":0,"color":"Emerald","rarity":"Rare","set":"010","num":100},"woody - leader of the toys":{"name":"Woody - Leader of the Toys","qty":7,"foil":0,"color":"Amber","rarity":"Uncommon","set":"012","num":21},"aurora - holding court":{"name":"Aurora - Holding Court","qty":2,"foil":0,"color":"Amber","rarity":"Uncommon","set":"009","num":6},"be our guest":{"name":"Be Our Guest","qty":9,"foil":0,"color":"Amber","rarity":"Common","set":"009","num":31},"stitch - alien dancer":{"name":"Stitch - Alien Dancer","qty":2,"foil":0,"color":"Amber","rarity":"Common","set":"009","num":9},"grandmother willow - ancient advisor":{"name":"Grandmother Willow - Ancient Advisor","qty":4,"foil":0,"color":"Amber","rarity":"Uncommon","set":"011","num":13},"mickey mouse - amber champion":{"name":"Mickey Mouse - Amber Champion","qty":4,"foil":0,"color":"Amber","rarity":"Rare","set":"010","num":23},"raging storm":{"name":"Raging Storm","qty":4,"foil":0,"color":"Amber","rarity":"Super Rare","set":"011","num":28},"mulan - free spirit":{"name":"Mulan - Free Spirit","qty":3,"foil":0,"color":"Amber","rarity":"Common","set":"009","num":10},"beast - gracious prince":{"name":"Beast - Gracious Prince","qty":1,"foil":0,"color":"Amber","rarity":"Rare","set":"009","num":4},"cinderella - gentle and kind":{"name":"Cinderella - Gentle and Kind","qty":3,"foil":0,"color":"Amber","rarity":"Uncommon","set":"009","num":19},"world's greatest criminal mind":{"name":"World's Greatest Criminal Mind","qty":2,"foil":0,"color":"Amber","rarity":"Uncommon","set":"009","num":30},"ariel - singing mermaid":{"name":"Ariel - Singing Mermaid","qty":1,"foil":1,"color":"Amber","rarity":"Rare","set":"009","num":15},"lost in the woods":{"name":"Lost in the Woods","qty":3,"foil":0,"color":"Amber","rarity":"Common","set":"009","num":28},"nani - protective sister":{"name":"Nani - Protective Sister","qty":2,"foil":0,"color":"Amber","rarity":"Uncommon","set":"009","num":17},"julieta madrigal - excellent cook":{"name":"Julieta Madrigal - Excellent Cook","qty":2,"foil":0,"color":"Amber","rarity":"Uncommon","set":"009","num":18},"mowgli - man cub":{"name":"Mowgli - Man Cub","qty":4,"foil":0,"color":"Amber","rarity":"Super Rare","set":"010","num":19},"rapunzel - sunshine":{"name":"Rapunzel - Sunshine","qty":3,"foil":0,"color":"Amber","rarity":"Common","set":"009","num":8},"akood et emuti":{"name":"Akood et Emuti","qty":4,"foil":0,"color":"Amber","rarity":"Rare","set":"011","num":29},"angel - siren singer":{"name":"Angel - Siren Singer","qty":4,"foil":0,"color":"Amber","rarity":"Uncommon","set":"011","num":25},"ariel - ethereal voice":{"name":"Ariel - Ethereal Voice","qty":4,"foil":0,"color":"Amber","rarity":"Rare","set":"010","num":17},"della's moon lullaby":{"name":"Della's Moon Lullaby","qty":7,"foil":0,"color":"Amber","rarity":"Common","set":"010","num":28},"look at this family":{"name":"Look at This Family","qty":1,"foil":0,"color":"Amber","rarity":"Rare","set":"009","num":25},"pluto - rescue dog":{"name":"Pluto - Rescue Dog","qty":3,"foil":0,"color":"Amber","rarity":"Common","set":"009","num":16},"heihei - bumbling rooster":{"name":"Heihei - Bumbling Rooster","qty":1,"foil":0,"color":"Emerald","rarity":"Uncommon","set":"009","num":86},"belle - untrained mystic":{"name":"Belle - Untrained Mystic","qty":1,"foil":0,"color":"Amethyst","rarity":"Common","set":"009","num":39},"aladdin - prince ali":{"name":"Aladdin - Prince Ali","qty":1,"foil":0,"color":"Emerald","rarity":"Common","set":"009","num":92},"lonely grave":{"name":"Lonely Grave","qty":4,"foil":0,"color":"Ruby","rarity":"Uncommon","set":"011","num":132},"copper - on the scent":{"name":"Copper - On the Scent","qty":4,"foil":0,"color":"Ruby","rarity":"Uncommon","set":"011","num":107},"dinner bell":{"name":"Dinner Bell","qty":1,"foil":0,"color":"Ruby","rarity":"Rare","set":"009","num":135},"hercules - spectral demigod":{"name":"Hercules - Spectral Demigod","qty":4,"foil":0,"color":"Ruby","rarity":"Common","set":"011","num":117},"powerline - taking the stage":{"name":"Powerline - Taking the Stage","qty":1,"foil":0,"color":"Ruby","rarity":"Common","set":"009","num":109},"a pirate's life":{"name":"A Pirate’s Life","qty":1,"foil":1,"color":"Ruby","rarity":"Uncommon","set":"009","num":132},"scrooge's counting house - ebenezer's office":{"name":"Scrooge's Counting House - Ebenezer's Office","qty":4,"foil":0,"color":"Ruby","rarity":"Uncommon","set":"011","num":134},"hermes - harried messenger":{"name":"Hermes - Harried Messenger","qty":4,"foil":0,"color":"Ruby","rarity":"Common","set":"010","num":112},"aladdin - barreling through":{"name":"Aladdin - Barreling Through","qty":4,"foil":0,"color":"Ruby","rarity":"Rare","set":"010","num":123},"grab your bow":{"name":"Grab Your Bow","qty":4,"foil":0,"color":"Ruby","rarity":"Uncommon","set":"011","num":131},"liquidator - iced over":{"name":"Liquidator - Iced Over","qty":4,"foil":0,"color":"Ruby","rarity":"Uncommon","set":"011","num":111},"mulan - standing her ground":{"name":"Mulan - Standing Her Ground","qty":4,"foil":0,"color":"Ruby","rarity":"Uncommon","set":"010","num":126},"ares - god of war":{"name":"Ares - God of War","qty":7,"foil":0,"color":"Ruby","rarity":"Uncommon","set":"010","num":104},"queen of hearts - sensing weakness":{"name":"Queen of Hearts - Sensing Weakness","qty":1,"foil":0,"color":"Ruby","rarity":"Uncommon","set":"009","num":120},"alice - accidentally adrift":{"name":"Alice - Accidentally Adrift","qty":3,"foil":2,"color":"Sapphire","rarity":"Promo","set":"009","num":2},"let it go":{"name":"Let it Go","qty":1,"foil":0,"color":"Sapphire","rarity":"Promo","set":"001","num":10},"mulan - considerate diplomat":{"name":"Mulan - Considerate Diplomat","qty":1,"foil":1,"color":"Sapphire","rarity":"Super Rare","set":"009","num":142},"tinker bell - tiny tactician":{"name":"Tinker Bell - Tiny Tactician","qty":1,"foil":0,"color":"Steel","rarity":"Common","set":"009","num":189},"hans - noble scoundrel":{"name":"Hans - Noble Scoundrel","qty":3,"foil":0,"color":"Sapphire","rarity":"Common","set":"009","num":148},"jasmine - heir of agrabah":{"name":"Jasmine - Heir of Agrabah","qty":3,"foil":0,"color":"Sapphire","rarity":"Common","set":"009","num":155},"dig a little deeper":{"name":"Dig a Little Deeper","qty":1,"foil":0,"color":"Sapphire","rarity":"Uncommon","set":"009","num":166},"motunui - island paradise":{"name":"Motunui - Island Paradise","qty":2,"foil":0,"color":"Sapphire","rarity":"Uncommon","set":"009","num":170},"coconut basket":{"name":"Coconut Basket","qty":3,"foil":0,"color":"Sapphire","rarity":"Common","set":"009","num":169},"aurora - regal princess":{"name":"Aurora - Regal Princess","qty":2,"foil":0,"color":"Sapphire","rarity":"Uncommon","set":"009","num":161},"mufasa - king of the pride lands":{"name":"Mufasa - King of the Pride Lands","qty":3,"foil":0,"color":"Sapphire","rarity":"Common","set":"009","num":144},"the queen - mirror seeker":{"name":"The Queen - Mirror Seeker","qty":1,"foil":0,"color":"Sapphire","rarity":"Uncommon","set":"009","num":149},"aurelian gyrosensor":{"name":"Aurelian Gyrosensor","qty":2,"foil":0,"color":"Sapphire","rarity":"Uncommon","set":"009","num":167},"belle - inventive engineer":{"name":"Belle - Inventive Engineer","qty":2,"foil":0,"color":"Sapphire","rarity":"Uncommon","set":"009","num":156},"grand pabbie - oldest and wisest":{"name":"Grand Pabbie - Oldest and Wisest","qty":1,"foil":0,"color":"Sapphire","rarity":"Rare","set":"009","num":150},"maid marian - delightful dreamer":{"name":"Maid Marian - Delightful Dreamer","qty":3,"foil":0,"color":"Sapphire","rarity":"Common","set":"009","num":158},"aurora - tranquil princess":{"name":"Aurora - Tranquil Princess","qty":3,"foil":0,"color":"Sapphire","rarity":"Common","set":"009","num":154},"anna - true-hearted":{"name":"Anna - True-Hearted","qty":2,"foil":0,"color":"Sapphire","rarity":"Rare","set":"009","num":137},"cruella de vil - fashionable cruiser":{"name":"Cruella De Vil - Fashionable Cruiser","qty":3,"foil":0,"color":"Sapphire","rarity":"Common","set":"009","num":145},"stitch - high badness level":{"name":"Stitch - High Badness Level","qty":2,"foil":2,"color":"Steel","rarity":"Promo","set":"011","num":35},"li shang - newly promoted":{"name":"Li Shang - Newly Promoted","qty":1,"foil":1,"color":"Ruby Steel","rarity":"Promo","set":"007","num":22},"rescue rangers away!":{"name":"Rescue Rangers Away!","qty":3,"foil":3,"color":"Amber","rarity":"Promo","set":"006","num":10},"the great illuminary - abandoned laboratory":{"name":"The Great Illuminary - Abandoned Laboratory","qty":3,"foil":3,"color":"Amethyst","rarity":"Promo","set":"010","num":19},"elsa - exploring the unknown":{"name":"Elsa - Exploring the Unknown","qty":2,"foil":2,"color":"Amethyst","rarity":"Promo","set":"010","num":22},"daisy duck - paranormal investigator":{"name":"Daisy Duck - Paranormal Investigator","qty":2,"foil":2,"color":"Sapphire","rarity":"Promo","set":"010","num":23},"the queen - conceited ruler":{"name":"The Queen - Conceited Ruler","qty":4,"foil":4,"color":"Amber","rarity":"Promo","set":"009","num":3},"scar - eerily prepared":{"name":"Scar - Eerily Prepared","qty":2,"foil":2,"color":"Sapphire","rarity":"Promo","set":"010","num":21},"cursed merfolk - ursula's handiwork":{"name":"Cursed Merfolk - Ursula's Handiwork","qty":2,"foil":2,"color":"Emerald","rarity":"Promo","set":"009","num":7},"dumbo - the flying elephant":{"name":"Dumbo - The Flying Elephant","qty":2,"foil":2,"color":"Amethyst","rarity":"Promo","set":"009","num":1},"honey lemon - chemical genius":{"name":"Honey Lemon - Chemical Genius","qty":2,"foil":2,"color":"Emerald","rarity":"Promo","set":"006","num":11},"you've got a friend in me":{"name":"You've Got a Friend in Me","qty":9,"foil":1,"color":"Amber","rarity":"Super Rare","set":"012","num":30},"rex - protective dinosaur":{"name":"Rex - Protective Dinosaur","qty":5,"foil":2,"color":"Amber","rarity":"Rare","set":"012","num":10},"the headless horseman - terror of sleepy hollow":{"name":"The Headless Horseman - Terror of Sleepy Hollow","qty":6,"foil":0,"color":"Ruby","rarity":"Legendary","set":"010","num":125},"medallion weights":{"name":"Medallion Weights","qty":6,"foil":1,"color":"Ruby","rarity":"Uncommon","set":"009","num":134},"gaston - frightful bully":{"name":"Gaston - Frightful Bully","qty":4,"foil":0,"color":"Amber","rarity":"Uncommon","set":"010","num":2},"reuben - sandwich expert":{"name":"Reuben - Sandwich Expert","qty":4,"foil":0,"color":"Amber","rarity":"Rare","set":"011","num":21},"stitch - carefree surfer":{"name":"Stitch - Carefree Surfer","qty":2,"foil":0,"color":"Amber","rarity":"Legendary","set":"009","num":24},"webby's diary":{"name":"Webby's Diary","qty":4,"foil":0,"color":"Amber","rarity":"Uncommon","set":"010","num":31},"mulan - injured soldier":{"name":"Mulan - Injured Soldier","qty":6,"foil":0,"color":"Ruby","rarity":"Common","set":"009","num":125},"bambi - ethereal fawn":{"name":"Bambi - Ethereal Fawn","qty":4,"foil":0,"color":"Amber","rarity":"Super Rare","set":"011","num":24},"mulan - elite archer":{"name":"Mulan - Elite Archer","qty":4,"foil":0,"color":"Ruby","rarity":"Super Rare","set":"009","num":126},"the sword of shan-yu":{"name":"The Sword of Shan-Yu","qty":1,"foil":0,"color":"Ruby","rarity":"Rare","set":"008","num":152},"scrooge mcduck - ghostly ebenezer":{"name":"Scrooge McDuck - Ghostly Ebenezer","qty":4,"foil":0,"color":"Ruby","rarity":"Uncommon","set":"011","num":104},"stitch - carefree snowboarder":{"name":"Stitch - Carefree Snowboarder","qty":4,"foil":0,"color":"Amber","rarity":"Rare","set":"011","num":7},"ohana means family":{"name":"Ohana Means Family","qty":4,"foil":0,"color":"Amber","rarity":"Legendary","set":"011","num":32},"the horseman strikes!":{"name":"The Horseman Strikes!","qty":3,"foil":0,"color":"Amber","rarity":"Rare","set":"010","num":29},"aladdin - resolute swordsman":{"name":"Aladdin - Resolute Swordsman","qty":1,"foil":0,"color":"Steel","rarity":"Common","set":"004","num":172},"cogsworth - majordomo":{"name":"Cogsworth - Majordomo","qty":1,"foil":0,"color":"Amber","rarity":"Common","set":"004","num":5},"marshmallow - terrifying snowman":{"name":"Marshmallow - Terrifying Snowman","qty":1,"foil":0,"color":"Amethyst","rarity":"Uncommon","set":"004","num":51},"ursula's garden - full of the unfortunate":{"name":"Ursula's Garden - Full of the Unfortunate","qty":1,"foil":0,"color":"Emerald","rarity":"Rare","set":"004","num":102},"daisy duck - lovely lady":{"name":"Daisy Duck - Lovely Lady","qty":1,"foil":0,"color":"Amber","rarity":"Uncommon","set":"004","num":6},"fortisphere":{"name":"Fortisphere","qty":1,"foil":1,"color":"Steel","rarity":"Common","set":"004","num":200},"pico - helpful toucan":{"name":"Pico - Helpful Toucan","qty":1,"foil":0,"color":"Amethyst","rarity":"Common","set":"004","num":55},"make the potion":{"name":"Make The Potion","qty":2,"foil":1,"color":"Emerald","rarity":"Common","set":"004","num":94},"poor unfortunate souls":{"name":"Poor Unfortunate Souls","qty":1,"foil":0,"color":"Amethyst","rarity":"Common","set":"004","num":60},"jaq - connoisseur of climbing":{"name":"Jaq - Connoisseur of Climbing","qty":1,"foil":0,"color":"Emerald","rarity":"Common","set":"004","num":77},"miracle candle":{"name":"Miracle Candle","qty":1,"foil":0,"color":"Amber","rarity":"Rare","set":"004","num":31},"rapunzel - appreciative artist":{"name":"Rapunzel - Appreciative Artist","qty":1,"foil":0,"color":"Sapphire","rarity":"Rare","set":"004","num":153},"hundred acre island - pooh's home":{"name":"Hundred Acre Island - Pooh's Home","qty":1,"foil":0,"color":"Amber","rarity":"Common","set":"006","num":34},"mullins - seasoned shipmate":{"name":"Mullins - Seasoned Shipmate","qty":1,"foil":0,"color":"Steel","rarity":"Common","set":"006","num":177},"scuttle - expert on humans":{"name":"Scuttle - Expert on Humans","qty":1,"foil":0,"color":"Sapphire","rarity":"Uncommon","set":"004","num":154},"glean":{"name":"Glean","qty":1,"foil":0,"color":"Sapphire","rarity":"Common","set":"004","num":163},"gold coin":{"name":"Gold Coin","qty":1,"foil":0,"color":"Ruby","rarity":"Common","set":"006","num":133},"imperial bow":{"name":"Imperial Bow","qty":1,"foil":0,"color":"Steel","rarity":"Uncommon","set":"004","num":201},"hidden inkcaster":{"name":"Hidden Inkcaster","qty":1,"foil":0,"color":"Emerald","rarity":"Common","set":"004","num":98},"thebes - the big olive":{"name":"Thebes - The Big Olive","qty":1,"foil":0,"color":"Steel","rarity":"Common","set":"004","num":204},"scrump":{"name":"Scrump","qty":1,"foil":0,"color":"Amber","rarity":"Uncommon","set":"006","num":33},"the fates - only one eye":{"name":"The Fates - Only One Eye","qty":1,"foil":0,"color":"Emerald","rarity":"Common","set":"004","num":89},"transformed chef - castle stove":{"name":"Transformed Chef - Castle Stove","qty":1,"foil":0,"color":"Sapphire","rarity":"Common","set":"004","num":157},"a very merry unbirthday":{"name":"A Very Merry Unbirthday","qty":1,"foil":1,"color":"Amethyst","rarity":"Common","set":"006","num":60},"olaf - trusting companion":{"name":"Olaf - Trusting Companion","qty":1,"foil":0,"color":"Sapphire","rarity":"Common","set":"004","num":150},"pascal - inquisitive pet":{"name":"Pascal - Inquisitive Pet","qty":1,"foil":0,"color":"Sapphire","rarity":"Common","set":"004","num":151},"pegasus - flying steed":{"name":"Pegasus - Flying Steed","qty":1,"foil":0,"color":"Ruby","rarity":"Common","set":"004","num":120},"chip - friend indeed":{"name":"Chip - Friend Indeed","qty":1,"foil":0,"color":"Amber","rarity":"Common","set":"006","num":6},"max - loyal sheepdog":{"name":"Max - Loyal Sheepdog","qty":2,"foil":0,"color":"Amber","rarity":"Common","set":"004","num":14},"yao - imperial soldier":{"name":"Yao - Imperial Soldier","qty":2,"foil":0,"color":"Steel","rarity":"Common","set":"004","num":194},"snuggly duckling - disreputable pub":{"name":"Snuggly Duckling - Disreputable Pub","qty":1,"foil":0,"color":"Ruby","rarity":"Rare","set":"004","num":135},"khan - beloved steed":{"name":"Khan - Beloved Steed","qty":1,"foil":0,"color":"Ruby","rarity":"Uncommon","set":"004","num":110},"rose lantern":{"name":"Rose Lantern","qty":2,"foil":1,"color":"Amethyst","rarity":"Common","set":"004","num":65},"ursula - mad sea witch":{"name":"Ursula - Mad Sea Witch","qty":1,"foil":0,"color":"Amethyst","rarity":"Uncommon","set":"004","num":57},"donald duck - musketeer soldier":{"name":"Donald Duck - Musketeer Soldier","qty":1,"foil":0,"color":"Amber","rarity":"Uncommon","set":"004","num":8},"pegasus - gift for hercules":{"name":"Pegasus - Gift for Hercules","qty":1,"foil":0,"color":"Emerald","rarity":"Common","set":"004","num":84},"sisu - daring visitor":{"name":"Sisu - Daring Visitor","qty":1,"foil":0,"color":"Ruby","rarity":"Uncommon","set":"004","num":123},"alma madrigal - family matriarch":{"name":"Alma Madrigal - Family Matriarch","qty":1,"foil":0,"color":"Amber","rarity":"Rare","set":"004","num":2},"prepare to board!":{"name":"Prepare To Board!","qty":1,"foil":0,"color":"Emerald","rarity":"Common","set":"006","num":94},"mosquito bite":{"name":"Mosquito Bite","qty":1,"foil":0,"color":"Emerald","rarity":"Uncommon","set":"006","num":96},"zeus - mr. lightning bolts":{"name":"Zeus - Mr. Lightning Bolts","qty":1,"foil":0,"color":"Emerald","rarity":"Super Rare","set":"004","num":92},"dolores madrigal - easy listener":{"name":"Dolores Madrigal - Easy Listener","qty":1,"foil":0,"color":"Amethyst","rarity":"Common","set":"004","num":41},"peter pan - shadow catcher":{"name":"Peter Pan - Shadow Catcher","qty":1,"foil":0,"color":"Amethyst","rarity":"Uncommon","set":"006","num":58},"casa madrigal - casita":{"name":"Casa Madrigal - Casita","qty":1,"foil":0,"color":"Amethyst","rarity":"Common","set":"004","num":67},"pooh pirate ship":{"name":"Pooh Pirate Ship","qty":1,"foil":0,"color":"Amber","rarity":"Rare","set":"006","num":32},"megara - captivating cynic":{"name":"Megara - Captivating Cynic","qty":1,"foil":0,"color":"Emerald","rarity":"Common","set":"004","num":79},"anna - braving the storm":{"name":"Anna - Braving the Storm","qty":1,"foil":0,"color":"Sapphire","rarity":"Common","set":"004","num":137},"luisa madrigal - magically strong one":{"name":"Luisa Madrigal - Magically Strong One","qty":1,"foil":0,"color":"Amethyst","rarity":"Common","set":"004","num":47},"lumiere - fiery friend":{"name":"Lumiere - Fiery Friend","qty":1,"foil":0,"color":"Ruby","rarity":"Rare","set":"004","num":113},"mickey mouse - standard bearer":{"name":"Mickey Mouse - Standard Bearer","qty":1,"foil":1,"color":"Steel","rarity":"Common","set":"004","num":188},"goofy - super goof":{"name":"Goofy - Super Goof","qty":2,"foil":0,"color":"Ruby","rarity":"Rare","set":"004","num":107},"jasmine - desert warrior":{"name":"Jasmine - Desert Warrior","qty":1,"foil":1,"color":"Emerald","rarity":"Rare","set":"004","num":78},"panic - immortal sidekick":{"name":"Panic - Immortal Sidekick","qty":1,"foil":0,"color":"Emerald","rarity":"Uncommon","set":"004","num":82},"mad hatter's teapot":{"name":"Mad Hatter's Teapot","qty":1,"foil":0,"color":"Amethyst","rarity":"Common","set":"006","num":66},"hercules - daring demigod":{"name":"Hercules - Daring Demigod","qty":2,"foil":0,"color":"Ruby","rarity":"Uncommon","set":"004","num":109},"ling - imperial soldier":{"name":"Ling - Imperial Soldier","qty":1,"foil":0,"color":"Steel","rarity":"Uncommon","set":"004","num":183},"hiro hamada - team leader":{"name":"Hiro Hamada - Team Leader","qty":1,"foil":0,"color":"Sapphire","rarity":"Rare","set":"006","num":154},"bruno's return":{"name":"Bruno's Return","qty":1,"foil":0,"color":"Amber","rarity":"Uncommon","set":"004","num":26},"luisa madrigal - rock of the family":{"name":"Luisa Madrigal - Rock of the Family","qty":1,"foil":0,"color":"Steel","rarity":"Common","set":"004","num":184},"li shang - general's son":{"name":"Li Shang - General's Son","qty":1,"foil":0,"color":"Ruby","rarity":"Common","set":"004","num":111},"the black cauldron":{"name":"The Black Cauldron","qty":2,"foil":0,"color":"Amber","rarity":"Legendary","set":"010","num":32},"maleficent - monstrous dragon":{"name":"Maleficent - Monstrous Dragon","qty":4,"foil":0,"color":"Ruby","rarity":"Legendary","set":"009","num":108},"dumbo - ninth wonder of the universe":{"name":"Dumbo - Ninth Wonder of the Universe","qty":1,"foil":1,"color":"Amethyst","rarity":"Legendary","set":"009","num":45}},"colUpdated":"2026-07-12T02:33:13.105Z","variants":{"jasmine - desert warrior":"004 - 78 - Jasmine - Desert Warrior.jpg","li shang - newly promoted":"007 - 22 - Li Shang - Newly Promoted.jpg","beast - gracious prince":"009 - 4 - Beast - Gracious Prince.jpg","aurora - holding court":"009 - 6 - Aurora - Holding Court.jpg","ariel - singing mermaid":"009 - 15 - Ariel - Singing Mermaid.jpg","stitch - carefree surfer":"009 - 24 - Stitch - Carefree Surfer.jpg","look at this family":"009 - 25 - Look at This Family.jpg","elsa - exploring the unknown":"010 - 45 - Elsa - Exploring the Unknown.jpg","the horseman strikes!":"010 - 29 - The Horseman Strikes!.jpg","stitch - carefree snowboarder":"011 - 7 - Stitch - Carefree Snowboarder.jpg","raging storm":"011 - 28 - Raging Storm.jpg","ohana means family":"011 - 32 - Ohana Means Family.jpg","demona - scourge of the wyvern clan":"010 - 55 - Demona - Scourge of the Wyvern Clan.jpg","dumbo - ninth wonder of the universe":"009 - 45 - Dumbo - Ninth Wonder of the Universe.jpg","hades - looking for a deal":"010 - 56 - Hades - Looking for a Deal.jpg","frozone - super cool":"012 - 59 - Frozone - Super Cool.jpg","peter pan & tinker bell - fast friends":"013 - 60 - Peter Pan & Tinker Bell - Fast Friends.jpg","you've got a friend in me":"012 - 30 - You've Got a Friend in Me.jpg","mirage - super recruiter":"012 - 53 - Mirage - Super Recruiter.jpg","edna mode - fashion designer":"012 - 54 - Edna Mode - Fashion Designer.jpg","maleficent - imperious traveler":"012 - 55 - Maleficent - Imperious Traveler.jpg","luisa madrigal - confident climber":"012 - 60 - Luisa Madrigal - Confident Climber.jpg","dunbroch family tapestry":"012 - 67 - DunBroch Family Tapestry.jpg","lenny - toy binoculars":"012 - 79 - Lenny - Toy Binoculars.jpg","buzz lightyear - space ranger":"012 - 76 - Buzz Lightyear - Space Ranger.jpg","milo thatch - getting his hands dirty":"012 - 82 - Milo Thatch - Getting His Hands Dirty.jpg","alien - true believer":"012 - 83 - Alien - True Believer.jpg","donald duck - distracted traveler":"012 - 84 - Donald Duck - Distracted Traveler.jpg","buzz lightyear - jungle ranger":"012 - 91 - Buzz Lightyear - Jungle Ranger.jpg","cruella de vil - judgmental traveler":"012 - 92 - Cruella De Vil - Judgmental Traveler.jpg","the family scattered":"012 - 97 - The Family Scattered.jpg","woody - waiting for a friend":"012 - 3 - Woody - Waiting for a Friend.jpg","mulan - injured soldier":"009 - 125 - Mulan - Injured Soldier.jpg","mulan - elite archer":"009 - 126 - Mulan - Elite Archer.jpg","medallion weights":"009 - 134 - Medallion Weights.jpg","sulley & boo - scare buddies":"013 - 29 - Sulley & Boo - Scare Buddies.jpg","woody & buzz lightyear - best buddies":"013 - 28 - Woody & Buzz Lightyear - Best Buddies.jpg","doc - taking notes":"012 - 40 - Doc - Taking Notes.jpg","merida - gifted archer":"012 - 89 - Merida - Gifted Archer.jpg","meilin lee - lead vocalist":"013 - 7 - Meilin Lee - Lead Vocalist.jpg","pocahontas & meeko - adventurous friends":"013 - 27 - Pocahontas & Meeko - Adventurous Friends.jpg","the madrigal family - every generation":"013 - 30 - The Madrigal Family - Every Generation.jpg","lilo & stitch - fun-loving friends":"013 - 31 - Lilo & Stitch - Fun-Loving Friends.jpg","winnie the pooh - hunny archmage":"013 - 40 - Winnie the Pooh - Hunny Archmage.jpg","vixey - expert fisher":"013 - 46 - Vixey - Expert Fisher.jpg","merida - wisp conjurer":"013 - 50 - Merida - Wisp Conjurer.jpg"},"variantsUpdated":"2026-07-12T04:53:50.309Z","deletedGames":["g6tj2q59"],"deletedDecks":["dmjvprs","dnr395s"]}