{"v":1,"updated":"2026-07-14T17:35:51.211Z","store":{"dra6mqt":[]},"lib":[{"id":"dra6mqt","title":"Detectives","inks":["steel","sapphire"],"arch":"Sapphire/Steel challenge midrange — ramp into durable Detectives, use Shift characters and Resist to dominate combat, then turn every successful challenge into cards and bonus lore.","tagline":"Solve the case, win the fight, collect the lore.","strategy":"Core strategy\n\nThis deck does not want to race by questing immediately. It wants to build a board of Detectives, make extremely efficient challenges, and profit every time an opposing character is banished.\n\nYour ideal development is:\n\nNick Wilde → Darkwing Duck or Judy → ramp/value item → Shift payoff → repeated challenge turns.\n\nEarly game\n\nYour best opening characters are:\n\nNick Wilde – Sly Fox Sleuth: cheap Detective and Shift target.\nDarkwing Duck – Drake Mallard: a 2-cost, 4-Strength Darkwing with Ward. He pressures fragile characters and enables both large Darkwing Shift options.\nJudy Hopps – Snowball Patrol: especially strong when playing second because she can cost 1 on your first turn.\nDarkwing’s Chair Set: ramps one card from the top of your deck into the inkwell, accelerating your expensive characters. It can later be banished to remove up to 4 damage from a Darkwing.\n\nDo not challenge recklessly with your small Nick or Judy when they are your only Shift targets. Preserving one base character can be more valuable than making a minor trade.\n\nMain value engine\nNick Wilde – Persistent Investigator\n\nShift Nick for 3 whenever possible. During your turn, each time one of your Detectives banishes an opposing character in a challenge, Nick draws a card. This turns combat from a one-for-one exchange into sustained card advantage.\n\nJudy Hopps – Lead Detective\n\nJudy is the deck’s main combat commander. During your turn, all your Detectives gain:\n\nAlert, allowing them to challenge Evasive characters.\nResist +2, making your challenges much safer.\n\nWith Mrs. Incredible – Determined Rescuer, your characters gain another Resist +1. A Detective can therefore have Resist +3 during your challenge turn, allowing it to survive fights that would normally trade evenly.\n\nRanger Plane\n\nRanger Plane gives all your characters Support. You can quest with a smaller character and transfer its Strength to the Detective that needs to make the important challenge. This allows your board to generate normal lore while preparing a stronger attack.\n\nChallenge-to-lore engine\n\nThe deck’s most important feature is that challenging becomes another way to win the lore race.\n\nThe Sword of Hercules: each time one of your characters banishes another character in a challenge during your turn, gain 1 lore.\nThe Thunderquack: after a character has been banished in a challenge, each Thunderquack can exert for 1 lore.\nDarkwing Duck & Launchpad – St. Canard’s Finest: gains 2 lore whenever it banishes another character in a challenge.\nNick Wilde – Persistent Investigator: draws a card when one of your Detectives makes that banish.\nAbsorbing Bloom: can draw a card after a challenge banish.\n\nA single successful challenge can therefore produce:\n\nBoard removal + card draw + 2 or more bonus lore.\n\nWith several payoff items in play, you can win without exposing your entire board by questing.\n\nDarkwing combo\n\nThe Thunderquack gives every opposing character the Villain classification. Darkwing Duck – Cool Under Pressure can challenge ready Villains, so the opponent cannot protect key characters simply by leaving them ready.\n\nCool Under Pressure also triggers whenever an item is banished. You may pay 1 ink to deal 2 damage to a chosen character. The cleanest interaction is:\n\nBanish Darkwing’s Chair Set.\nRemove up to 4 damage from a Darkwing.\nPay 1 with Cool Under Pressure to deal 2 damage.\nDarkwarrior gains Resist +1 from the banished item.\nFinish the damaged opposing character in a challenge.\n\nThis creates removal, healing and combat protection from one item.\n\nRemoval package\n\nUse your removal to prepare profitable challenges rather than spending it automatically:\n\nThe Terror That Flaps in the Night: deals 2 damage, or 3 while you control a Darkwing.\nHe Hurled His Thunderbolt: deals 4 damage.\nLet It Go: answers large characters that are too difficult or dangerous to challenge.\nJudy Hopps – On the Case: can place an opposing item into its owner’s inkwell when you already control another Detective.\n\nDamage actions are often best used to soften a character so one of your Detectives can finish it. That final challenge activates Nick, Thunderquack, Sword, Bloom and St. Canard’s Finest.\n\nPrimary win conditions\n1. Repeated Detective challenges\n\nEstablish Nick and Judy, then continuously banish characters while drawing replacements and protecting your board with Resist.\n\n2. Darkwing & Launchpad challenge turns\n\nShift it for 5 onto an inexpensive Darkwing. It has Ward, 5 Strength, 7 Willpower and earns 2 lore for each character it banishes in a challenge. Support and Judy’s Resist make it difficult to stop in combat.\n\n3. Traditional questing\n\nAgainst decks that offer few challenge targets, use your durable characters to quest normally. Judy Uncovering Clues helps maintain your hand by finding another Detective when played and whenever she quests.\n\nMulligan\nPrioritize\nNick Wilde – Sly Fox Sleuth\nDarkwing Duck – Drake Mallard\nJudy Hopps – Snowball Patrol when playing second\nDarkwing’s Chair Set with an early character\nNick Wilde – Persistent Investigator alongside Nick\nJudy Hopps – Lead Detective alongside a cheaper Judy\nOne Darkwing Shift payoff alongside Drake Mallard\nUsually return\nMultiple copies of Let It Go\nMrs. Incredible without sufficient early plays\nStandalone 7-cost characters without Shift targets\nThe Sword of Hercules unless the rest of the hand already curves well\nAbsorbing Bloom without early characters capable of challenging\nMain weakness\n\nThe deck is heavily dependent on maintaining characters and suitable Shift targets. Early removal aimed at Nick, Judy and Darkwing can leave expensive cards stranded in your hand. Preserve your Shift bases when possible, and do not ink all copies of your smaller named characters just because you already have one in play.","cards":["4 Let It Go","4 Judy Hopps - Uncovering Clues","2 He Hurled His Thunderbolt","4 Nick Wilde - Sly Fox Sleuth","4 Darkwing Duck - Drake Mallard","4 Darkwing's Chair Set","3 The Thunderquack","4 The Terror That Flaps in the Night","2 Judy Hopps - On the Case","1 The Sword of Hercules","2 Ranger Plane","2 Judy Hopps - Snowball Patrol","3 Mrs. Incredible - Determined Rescuer","4 Darkwing Duck - Cool Under Pressure","4 Nick Wilde - Persistent Investigator","4 Judy Hopps - Lead Detective","4 Darkwing Duck - Darkwarrior","4 Darkwing Duck & Launchpad - St. Canard's Finest","1 Absorbing Bloom"],"mtime":"2026-07-14T17:32:45.457Z","heroArts":["Judy Hopps - Uncovering Clues","Darkwing Duck & Launchpad - St. Canard's Finest","Nick Wilde - Persistent Investigator"]}],"collection":{"you've got a friend in me":{"name":"You've Got a Friend in Me","qty":1,"foil":1,"color":"Amber","rarity":"Super Rare","set":"012","num":30}},"colUpdated":"2026-07-14T01:46:22.199Z","variants":{"jasmine - desert warrior":"004 - 78 - Jasmine - Desert Warrior.jpg","li shang - newly promoted":"007 - 22 - Li Shang - Newly Promoted.jpg","beast - gracious prince":"009 - 4 - Beast - Gracious Prince.jpg","aurora - holding court":"009 - 6 - Aurora - Holding Court.jpg","ariel - singing mermaid":"009 - 15 - Ariel - Singing Mermaid.jpg","stitch - carefree surfer":"009 - 24 - Stitch - Carefree Surfer.jpg","look at this family":"009 - 25 - Look at This Family.jpg","elsa - exploring the unknown":"010 - 45 - Elsa - Exploring the Unknown.jpg","the horseman strikes!":"010 - 29 - The Horseman Strikes!.jpg","stitch - carefree snowboarder":"011 - 7 - Stitch - Carefree Snowboarder.jpg","raging storm":"011 - 28 - Raging Storm.jpg","ohana means family":"011 - 32 - Ohana Means Family.jpg","demona - scourge of the wyvern clan":"010 - 55 - Demona - Scourge of the Wyvern Clan.jpg","dumbo - ninth wonder of the universe":"009 - 45 - Dumbo - Ninth Wonder of the Universe.jpg","hades - looking for a deal":"010 - 56 - Hades - Looking for a Deal.jpg","frozone - super cool":"012 - 59 - Frozone - Super Cool.jpg","peter pan & tinker bell - fast friends":"013 - 60 - Peter Pan & Tinker Bell - Fast Friends.jpg","you've got a friend in me":"012 - 30 - You've Got a Friend in Me.jpg","mirage - super recruiter":"012 - 53 - Mirage - Super Recruiter.jpg","edna mode - fashion designer":"012 - 54 - Edna Mode - Fashion Designer.jpg","maleficent - imperious traveler":"012 - 55 - Maleficent - Imperious Traveler.jpg","luisa madrigal - confident climber":"012 - 60 - Luisa Madrigal - Confident Climber.jpg","dunbroch family tapestry":"012 - 67 - DunBroch Family Tapestry.jpg","lenny - toy binoculars":"012 - 79 - Lenny - Toy Binoculars.jpg","buzz lightyear - space ranger":"012 - 76 - Buzz Lightyear - Space Ranger.jpg","milo thatch - getting his hands dirty":"012 - 82 - Milo Thatch - Getting His Hands Dirty.jpg","alien - true believer":"012 - 83 - Alien - True Believer.jpg","donald duck - distracted traveler":"012 - 84 - Donald Duck - Distracted Traveler.jpg","buzz lightyear - jungle ranger":"012 - 91 - Buzz Lightyear - Jungle Ranger.jpg","cruella de vil - judgmental traveler":"012 - 92 - Cruella De Vil - Judgmental Traveler.jpg","the family scattered":"012 - 97 - The Family Scattered.jpg","woody - waiting for a friend":"012 - 3 - Woody - Waiting for a Friend.jpg","mulan - injured soldier":"009 - 125 - Mulan - Injured Soldier.jpg","mulan - elite archer":"009 - 126 - Mulan - Elite Archer.jpg","medallion weights":"009 - 134 - Medallion Weights.jpg","sulley & boo - scare buddies":"013 - 29 - Sulley & Boo - Scare Buddies.jpg","woody & buzz lightyear - best buddies":"013 - 28 - Woody & Buzz Lightyear - Best Buddies.jpg","doc - taking notes":"012 - 40 - Doc - Taking Notes.jpg","merida - gifted archer":"012 - 89 - Merida - Gifted Archer.jpg","meilin lee - lead vocalist":"013 - 7 - Meilin Lee - Lead Vocalist.jpg","pocahontas & meeko - adventurous friends":"013 - 27 - Pocahontas & Meeko - Adventurous Friends.jpg","the madrigal family - every generation":"013 - 30 - The Madrigal Family - Every Generation.jpg","lilo & stitch - fun-loving friends":"013 - 31 - Lilo & Stitch - Fun-Loving Friends.jpg","winnie the pooh - hunny archmage":"013 - 40 - Winnie the Pooh - Hunny Archmage.jpg","vixey - expert fisher":"013 - 46 - Vixey - Expert Fisher.jpg","merida - wisp conjurer":"013 - 50 - Merida - Wisp Conjurer.jpg","mrs. incredible - created by the vine":"013 - 51 - Mrs. Incredible - Created by the Vine.jpg","heihei - created by the vine":"013 - 54 - HeiHei - Created by the Vine.jpg","aladdin & genie - mischievous pals":"013 - 59 - Aladdin & Genie - Mischievous Pals.jpg","winnie the pooh & piglet - hunny mages":"013 - 62 - Winnie the Pooh & Piglet - Hunny Mages.jpg","buzz lightyear - providing cover":"013 - 77 - Buzz Lightyear - Providing Cover.jpg","kevin - flightless bird":"013 - 88 - Kevin - Flightless Bird.jpg","peter pan - created by the vine":"013 - 89 - Peter Pan - Created by the Vine.jpg","mother gothel - evil as ever":"013 - 93 - Mother Gothel - Evil as Ever.jpg","tod & copper - best of friends":"013 - 94 - Tod & Copper - Best of Friends.jpg","rapunzel - escaping the tower":"013 - 95 - Rapunzel - Escaping the Tower.jpg","mickey mouse & minnie mouse - adventuring duo":"013 - 99 - Mickey Mouse & Minnie Mouse - Adventuring Duo.jpg","carl fredricksen & russell - intrepid explorers":"013 - 98 - Carl Fredricksen & Russell - Intrepid Explorers.jpg","randall boggs - scary smart":"013 - 153 - Randall Boggs - Scary Smart.jpg","the black cauldron":"010 - 32 - The Black Cauldron.jpg","let it go":"001 - 163 - Let It Go.jpg"},"variantsUpdated":"2026-07-14T17:32:54.110Z","deletedGames":["g1zwdvez"],"deletedDecks":["dale","sid","woody"]}